brave_search/__init__.py
brave_search/server.py
mcp_brave_search-0.1.1.dist-info/licenses/LICENSE
mcp_brave_search-0.1.1.dist-info/METADATA
mcp_brave_search-0.1.1.dist-info/WHEEL
mcp_brave_search-0.1.1.dist-info/entry_points.txt
mcp_brave_search-0.1.1.dist-info/top_level.txt
mcp_brave_search-0.1.1.dist-info/RECORD
