Metadata-Version: 2.4
Name: mcp-brave-search
Version: 0.1.1
Summary: MCP server for Brave Search API, providing web and local search capabilities
Author-email: manoj48 <manojwork385@gmail.com>
License: MIT
Classifier: Programming Language :: Python :: 3
Classifier: License :: OSI Approved :: MIT License
Classifier: Operating System :: OS Independent
Requires-Python: >=3.9
License-File: LICENSE
Requires-Dist: mcp>=1.2.0
Requires-Dist: httpx>=0.27.0
Requires-Dist: python-dotenv>=1.0.1
Dynamic: license-file
